w3crack/__init__.py
w3crack/wcrack.so
w3crack-0.1.0.dist-info/LICENSE
w3crack-0.1.0.dist-info/METADATA
w3crack-0.1.0.dist-info/WHEEL
w3crack-0.1.0.dist-info/top_level.txt
w3crack-0.1.0.dist-info/RECORD
