Metadata-Version: 2.1
Name: w3crack
Version: 0.1.0
Summary: Web3 Wallet bruteforce using CPU and GPU
Author: PepeIC
Project-URL: Homepage, https://github.com/pepeic/w3crack_driver
Keywords: web3,wallet,recovery,restore,bruteforce,bitcoin,ethereum,metamask,trust,trustwallet,brave,bravewallet
Classifier: Programming Language :: Python :: 3.7
Classifier: Programming Language :: Python :: 3.8
Classifier: Programming Language :: Python :: 3.9
Classifier: Programming Language :: Python :: 3.10
Classifier: Programming Language :: Python :: 3.11
Classifier: Programming Language :: Python :: 3.12
Classifier: License :: OSI Approved :: MIT License
Classifier: Operating System :: Microsoft :: Windows
Classifier: Operating System :: POSIX :: Linux
Requires-Python: >=3.7
License-File: LICENSE
